{
  "宅": [
    {
      "name": "螺",
      "emoji": "🐚"
    },
    {
      "name": "贝",
      "emoji": "🦪"
    },
    {
      "name": "龟",
      "emoji": "🐢"
    }
  ],
  "屋": "宅",
  "祭祀": [
    {
      "name": "鸡",
      "emoji": "🐥"
    },
    {
      "name": "鸭",
      "emoji": "🦆"
    },
    {
      "name": "鱼",
      "emoji": "🐟"
    },
    {
      "name": "猪",
      "emoji": "🐷"
    },
    {
      "name": "糕点",
      "emoji": "🎂"
    },
    {
      "name": "水果",
      "emoji": "🍎"
    }
  ],
  "安葬": [
    {
      "name": "罐头",
      "emoji": "🥫"
    },
    {
      "name": "速食",
      "emoji": "🧊"
    }
  ],
  "嫁娶": [
    {
      "name": "肉",
      "emoji": "🥩"
    },
    {
      "name": "常见海鲜",
      "emoji": "🦞"
    },
    {
      "name": "酒",
      "emoji": "🍺"
    }
  ],
  "出行": [
    {
      "name": "鸟",
      "emoji": "🐦"
    },
    {
      "name": "鱼",
      "emoji": "🐟"
    },
    {
      "name": "鹿",
      "emoji": "🦌"
    },
    {
      "name": "酒",
      "emoji": "🍺"
    }
  ],
  "祈福": [
    {
      "name": "面食",
      "emoji": "🥡"
    }
  ],
  "动土": [
    {
      "name": "菌类",
      "emoji": "🍄"
    },
    {
      "name": "常见蔬菜",
      "emoji": "🥬"
    },
    {
      "name": "药材",
      "emoji": "🌿"
    },
    {
      "name": "坚果",
      "emoji": "🥜"
    },
    {
      "name": "花",
      "emoji": "🌺"
    }
  ],
  "栽种": "动土",
  "平治道涂": "动土",
  "作灶": "动土",
  "安床": [
    {
      "name": "菌类",
      "emoji": "🍄"
    },
    {
      "name": "蜗牛",
      "emoji": "🐌"
    },
    {
      "name": "螺",
      "emoji": "🐚"
    },
    {
      "name": "鸟",
      "emoji": "🐦"
    },
    {
      "name": "贝",
      "emoji": "🦪"
    }
  ],
  "开光": [
    {
      "name": "常见蔬菜",
      "emoji": "🥬"
    },
    {
      "name": "花",
      "emoji": "🌺"
    }
  ],
  "采纳": [
    {
      "name": "糖",
      "emoji": "🍬"
    },
    {
      "name": "酒",
      "emoji": "🍺"
    }
  ],
  "入殓": [
    {
      "name": "猪",
      "emoji": "🐷"
    },
    {
      "name": "面",
      "emoji": "🍜"
    },
    {
      "name": "酒",
      "emoji": "🍺"
    }
  ],
  "移徙": [
    {
      "name": "虫",
      "emoji": "🐛"
    },
    {
      "name": "鸟",
      "emoji": "🐦"
    },
    {
      "name": "鱼",
      "emoji": "🐟"
    },
    {
      "name": "鹿",
      "emoji": "🦌"
    }
  ],
  "破土": "动土",
  "解除": [
    {
      "name": "蛇",
      "emoji": "🐍"
    },
    {
      "name": "螃蟹",
      "emoji": "🦀"
    },
    {
      "name": "水",
      "emoji": "💧"
    }
  ],
  "修造": [
    {
      "name": "鸟",
      "emoji": "🐦"
    },
    {
      "name": "河鲜",
      "emoji": "🦦"
    }
  ],
  "垣": [
    {
      "name": "贝",
      "emoji": "🦪"
    },
    {
      "name": "橙橘",
      "emoji": "🍊"
    },
    {
      "name": "蛋",
      "emoji": "🥚"
    }
  ],
  "诸事不宜": [
    {
      "name": "西北风",
      "emoji": "🌪️"
    }
  ],
  "事勿取": [
    {
      "name": "其他少吃",
      "emoji": "⚠️"
    }
  ],
  "治病": [
    {
      "name": "药材",
      "emoji": "🌿"
    },
    {
      "name": "黄瓜",
      "emoji": "🥒"
    },
    {
      "name": "西红柿",
      "emoji": "🍅"
    },
    {
      "name": "花菜",
      "emoji": "🥦"
    }
  ],
  "求医": "治病",
  "沐浴": [],
  "塑绘": [
    {
      "name": "番茄",
      "emoji": "🍅"
    },
    {
      "name": "胡萝卜",
      "emoji": "🥕"
    },
    {
      "name": "菠菜",
      "emoji": "🥬"
    },
    {
      "name": "墨鱼",
      "emoji": "🦑"
    },
    {
      "name": "草莓",
      "emoji": "🍓"
    }
  ],
  "纳畜": [
    {
      "name": "鸡",
      "emoji": "🐥"
    },
    {
      "name": "鸭",
      "emoji": "🦆"
    },
    {
      "name": "鱼",
      "emoji": "🐟"
    },
    {
      "name": "猪",
      "emoji": "🐷"
    }
  ],
  "牧养": "纳畜",
  "无": [
    {
      "name": "自己看着办吧",
      "emoji": "🍽️"
    }
  ],
  "开仓": [
    {
      "name": "面食",
      "emoji": "🥡"
    },
    {
      "name": "玉米",
      "emoji": "🌽"
    }
  ],
  "冠笄": [
    {
      "name": "面食",
      "emoji": "🥡"
    },
    {
      "name": "鱼",
      "emoji": "🐟"
    },
    {
      "name": "春卷",
      "emoji": "🌯"
    },
    {
      "name": "粥",
      "emoji": "🥣"
    }
  ]
}
